[[{"word":"a"},{"word":"about"},{"word":"act"},{"word":"actually"},{"word":"add"},{"word":"after"},{"word":"again"},{"word":"against"},{"word":"age"},{"word":"ago"},{"word":"air"},{"word":"all"},{"word":"also"},{"word":"always"},{"word":"as"},{"word":"ask"},{"word":"at"},{"word":"are"},{"word":"area"},{"word":"appear"},{"word":"answer"},{"word":"another"},{"word":"animal"},{"word":"and"},{"word":"an"},{"word":"among"}],[{"word":"back"},{"word":"ball"},{"word":"base"},{"word":"be"},{"word":"beauty"},{"word":"because"},{"word":"become"},{"word":"bed"},{"word":"been"},{"word":"before"},{"word":"began"},{"word":"begin"},{"word":"behind"},{"word":"best"},{"word":"better"},{"word":"between"},{"word":"big"},{"word":"bird"},{"word":"black"},{"word":"blue"},{"word":"boat"},{"word":"body"},{"word":"book"},{"word":"both"},{"word":"bottom"},{"word":"boy"},{"word":"bring"},{"word":"brought"},{"word":"build"},{"word":"built"},{"word":"busy"},{"word":"but"},{"word":" by"}],[{"word":"call"},{"word":"came"},{"word":"can"},{"word":"car"},{"word":"care"},{"word":"carefully"},{"word":"carry"},{"word":"centre"},{"word":"certain"},{"word":"change"},{"word":"check"},{"word":"child"},{"word":"children"},{"word":"city"},{"word":"class"},{"word":"clear"},{"word":"close"},{"word":"cold"},{"word":"colour"},{"word":"come"},{"word":"common"},{"word":"community"},{"word":"complete"},{"word":"contain"},{"word":"could"},{"word":"country"},{"word":"course"},{"word":"create"},{"word":"cried"},{"word":"cross"},{"word":"cry"},{"word":"cut"}],[{"word":"dark"},{"word":"day"},{"word":"decide"},{"word":"decided"},{"word":"deep"},{"word":"develop"},{"word":"did"},{"word":"didn’t"},{"word":"different"},{"word":"do"},{"word":"does"},{"word":"dog"},{"word":"don’t"},{"word":"down"},{"word":"draw"},{"word":"dream"},{"word":"drive"},{"word":"dry"},{"word":"during"}],[{"word":"each"},{"word":"early"},{"word":"earth"},{"word":"east"},{"word":"easy"},{"word":"eat"},{"word":"effort"},{"word":"enough"},{"word":"every"},{"word":"example"},{"word":"experience"},{"word":"explain"},{"word":"eye"}],[{"word":" by"},{"word":" by"},{"word":" by"},{"word":" by"},{"word":" by"},{"word":" by"},{"word":" by"},{"word":" by"},{"word":" by"},{"word":" by"},{"word":" by"},{"word":" by"},{"word":" by"},{"word":" by"},{"word":" by"},{"word":" by"},{"word":" by"},{"word":" by"},{"word":" by"},{"word":" by"},{"word":" by"},{"word":" by"},{"word":" by"},{"word":" by"},{"word":" by"},{"word":" by"},{"word":" by"},{"word":" by"},{"word":" by"},{"word":" by"},{"word":" by"},{"word":" by"},{"word":" by"},{"word":" by"},{"word":" by"},{"word":" by"},{"word":" by"},{"word":" by"},{"word":" by"},{"word":" by"},{"word":" by"},{"word":" by"},{"word":" by"},{"word":" by"},{"word":" by"},{"word":" by"},{"word":" by"},{"word":" by"},{"word":" by"},{"word":" by"},{"word":" by"},{"word":" by"},{"word":" by"},{"word":" by"},{"word":" by"},{"word":" by"},{"word":" by"},{"word":" by"},{"word":" by"},{"word":" by"},{"word":" by"},{"word":" by"},{"word":" by"},{"word":" by"},{"word":" by"},{"word":" by"},{"word":" by"},{"word":" by"},{"word":" by"},{"word":" by"},{"word":" by"},{"word":" by"},{"word":" by"},{"word":" by"},{"word":" by"},{"word":" by"},{"word":" by"},{"word":" by"},{"word":" by"},{"word":" by"},{"word":" by"},{"word":" by"},{"word":" by"},{"word":" by"},{"word":" by"},{"word":" by"},{"word":" by"},{"word":" by"},{"word":" by"},{"word":" by"},{"word":" by"},{"word":" by"},{"word":" by"},{"word":" by"},{"word":" by"},{"word":" by"},{"word":" by"}],
{"word":"hi"},{"word":"hi"},{"word":"hi"},{"word":"hi"}

  

  

]

